{
  "entry": "server.js",
  "files": {
    "components/address-list.js": "components/address-list.js",
    "components/addresses-list.js": "components/addresses-list.js",
    "components/authenticator.js": "components/authenticator.js",
    "components/cart-button.js": "components/cart-button.js",
    "components/chat-body.js": "components/chat-body.js",
    "components/chat-card.js": "components/chat-card.js",
    "components/chat-categories.js": "components/chat-categories.js",
    "components/chat-header.js": "components/chat-header.js",
    "components/chat-input.js": "components/chat-input.js",
    "components/chat-option.js": "components/chat-option.js",
    "components/chat-options.js": "components/chat-options.js",
    "components/choose-payment-processor.js": "components/choose-payment-processor.js",
    "components/google-btn.js": "components/google-btn.js",
    "components/home.js": "components/home.js",
    "components/landing-categories.js": "components/landing-categories.js",
    "components/landing-copy.js": "components/landing-copy.js",
    "components/landing-faq.js": "components/landing-faq.js",
    "components/landing-footer.js": "components/landing-footer.js",
    "components/landing-page.js": "components/landing-page.js",
    "components/landing.js": "components/landing.js",
    "components/loading-animation.js": "components/loading-animation.js",
    "components/order-display.js": "components/order-display.js",
    "components/otp-input.js": "components/otp-input.js",
    "pages/aboutus.js": "pages/aboutus.js",
    "pages/addresslist.js": "pages/addresslist.js",
    "pages/admin/checkout.js": "pages/admin/checkout.js",
    "pages/admin/dashboard.js": "pages/admin/dashboard.js",
    "pages/admin/index.js": "pages/admin/index.js",
    "pages/admin/order/index.js": "pages/admin/order/index.js",
    "pages/auth/googlecallback.js": "pages/auth/googlecallback.js",
    "pages/authp.js": "pages/authp.js",
    "pages/banipay.js": "pages/banipay.js",
    "pages/cart.js": "pages/cart.js",
    "pages/checkout.js": "pages/checkout.js",
    "pages/index.js": "pages/index.js",
    "pages/options.js": "pages/options.js",
    "pages/orders.js": "pages/orders.js",
    "pages/payment.js": "pages/payment.js",
    "pages/paystack.js": "pages/paystack.js",
    "pages/userorder/_orderid.js": "pages/userorder/_orderid.js",
    "server.js": "server.js"
  },
  "maps": {
    "components/address-list.js": "components/address-list.js.map",
    "components/addresses-list.js": "components/addresses-list.js.map",
    "components/authenticator.js": "components/authenticator.js.map",
    "components/cart-button.js": "components/cart-button.js.map",
    "components/chat-body.js": "components/chat-body.js.map",
    "components/chat-card.js": "components/chat-card.js.map",
    "components/chat-categories.js": "components/chat-categories.js.map",
    "components/chat-header.js": "components/chat-header.js.map",
    "components/chat-input.js": "components/chat-input.js.map",
    "components/chat-option.js": "components/chat-option.js.map",
    "components/chat-options.js": "components/chat-options.js.map",
    "components/choose-payment-processor.js": "components/choose-payment-processor.js.map",
    "components/google-btn.js": "components/google-btn.js.map",
    "components/home.js": "components/home.js.map",
    "components/landing-categories.js": "components/landing-categories.js.map",
    "components/landing-copy.js": "components/landing-copy.js.map",
    "components/landing-faq.js": "components/landing-faq.js.map",
    "components/landing-footer.js": "components/landing-footer.js.map",
    "components/landing-page.js": "components/landing-page.js.map",
    "components/landing.js": "components/landing.js.map",
    "components/loading-animation.js": "components/loading-animation.js.map",
    "components/order-display.js": "components/order-display.js.map",
    "components/otp-input.js": "components/otp-input.js.map",
    "pages/aboutus.js": "pages/aboutus.js.map",
    "pages/addresslist.js": "pages/addresslist.js.map",
    "pages/admin/checkout.js": "pages/admin/checkout.js.map",
    "pages/admin/dashboard.js": "pages/admin/dashboard.js.map",
    "pages/admin/index.js": "pages/admin/index.js.map",
    "pages/admin/order/index.js": "pages/admin/order/index.js.map",
    "pages/auth/googlecallback.js": "pages/auth/googlecallback.js.map",
    "pages/authp.js": "pages/authp.js.map",
    "pages/banipay.js": "pages/banipay.js.map",
    "pages/cart.js": "pages/cart.js.map",
    "pages/checkout.js": "pages/checkout.js.map",
    "pages/index.js": "pages/index.js.map",
    "pages/options.js": "pages/options.js.map",
    "pages/orders.js": "pages/orders.js.map",
    "pages/payment.js": "pages/payment.js.map",
    "pages/paystack.js": "pages/paystack.js.map",
    "pages/userorder/_orderid.js": "pages/userorder/_orderid.js.map",
    "server.js": "server.js.map"
  }
}